testfolio/__init__.py
testfolio/backtest.py
testfolio/utils.py
testfolio/visualize.py
testfolio-0.1.7.dist-info/LICENSE
testfolio-0.1.7.dist-info/WHEEL
testfolio-0.1.7.dist-info/METADATA
testfolio-0.1.7.dist-info/RECORD
