Metadata-Version: 2.1
Name: testfolio
Version: 0.1.7
Summary: Quick portfolio backtesting and visualization
Home-page: https://github.com/BradleyHe/testfolio
License: MIT
Keywords: portfolio,stock,backtest,finance,market
Author: Bradley He
Author-email: bhe6001@gmail.com
Requires-Python: >=3.6,<4.0
Classifier: License :: OSI Approved :: MIT License
Classifier: Operating System :: OS Independent
Classifier: Programming Language :: Python :: 3
Classifier: Programming Language :: Python :: 3.10
Classifier: Programming Language :: Python :: 3.6
Classifier: Programming Language :: Python :: 3.7
Classifier: Programming Language :: Python :: 3.8
Classifier: Programming Language :: Python :: 3.9
Classifier: Topic :: Office/Business :: Financial
Classifier: Topic :: Office/Business :: Financial :: Investment
Classifier: Topic :: Software Development :: Libraries
Classifier: Topic :: Software Development :: Libraries :: Python Modules
Requires-Dist: matplotlib (>=3.5.0)
Requires-Dist: pandas-datareader (>=0.10.0)
Requires-Dist: yfinance (>=0.1.70)
Project-URL: Repository, https://github.com/BradleyHe/testfolio
